scriptie/__init__.py
scriptie/scripts.py
scriptie/server.py
scriptie/static_files/client.js
scriptie/static_files/forms.js
scriptie/static_files/index.html
scriptie/static_files/main.css
scriptie/static_files/main.js
scriptie/static_files/preact_htm.js
scriptie/static_files/reset.css
scriptie-0.1.0.dist-info/METADATA
scriptie-0.1.0.dist-info/WHEEL
scriptie-0.1.0.dist-info/entry_points.txt
scriptie-0.1.0.dist-info/top_level.txt
scriptie-0.1.0.dist-info/RECORD
