Metadata-Version: 2.1
Name: scriptie
Version: 0.1.0
Requires-Dist: aiohttp
